ntap/LM.py
ntap/RNN.py
ntap/SVM.py
ntap/__init__.py
ntap/data.py
ntap/helpers.py
ntap/models.py
textmodels/__init__.py
textmodels/bagofwords.py
textmodels/summarize.py
textmodels/utils.py
textmodels/validation.py
textmodels/dic/__init__.py
textmodels/dic/_utils.py
textmodels/dic/base.py
textmodels/embed/__init__.py
textmodels/embed/_utils.py
textmodels/embed/base.py
textmodels/supervised/__init__.py
textmodels/supervised/_build.py
textmodels/supervised/_formula.py
textmodels/supervised/_summary.py
textmodels/supervised/base.py
textmodels-0.1.0.dist-info/METADATA
textmodels-0.1.0.dist-info/WHEEL
textmodels-0.1.0.dist-info/top_level.txt
textmodels-0.1.0.dist-info/RECORD
